cflare/__init__.py
cflare/lib/__init__.py
cflare/lib/models.py
cflare/utils/__init__.py
cflare/utils/cli.py
cflare/utils/logs.py
cflare-0.0.2.dist-info/LICENSE
cflare-0.0.2.dist-info/METADATA
cflare-0.0.2.dist-info/WHEEL
cflare-0.0.2.dist-info/entry_points.txt
cflare-0.0.2.dist-info/top_level.txt
cflare-0.0.2.dist-info/RECORD
