Metadata-Version: 2.1
Name: cflare
Version: 0.0.2
Summary: cflare
Home-page: http://github.com/trisongz/cflare
Author: Tri Songz
Author-email: ts@growthengineai.com
License: UNKNOWN
Platform: UNKNOWN
Classifier: Development Status :: 3 - Alpha
Classifier: Environment :: Console
Classifier: Intended Audience :: Developers
Requires-Python: >=3.6
Requires-Dist: dataclasses-json
Requires-Dist: requests
Requires-Dist: typer
